.flake8
CHANGELOG.md
LICENSE
MANIFEST.in
README.md
pyproject.toml
pytest.ini
requirements-dev.txt
requirements.txt
setup.py
tox.ini
docs/api_reference.md
docs/conf.py
docs/contributing.md
docs/index.md
docs/installation.md
docs/usage_guide.md
docs/source/api_reference.rst
docs/source/conf.py
docs/source/contributing.rst
docs/source/index.rst
docs/source/installation.rst
docs/source/usage_guide.rst
src/balochi_nlp/__init__.py
src/balochi_nlp/cli.py
src/balochi_nlp.egg-info/PKG-INFO
src/balochi_nlp.egg-info/SOURCES.txt
src/balochi_nlp.egg-info/dependency_links.txt
src/balochi_nlp.egg-info/not-zip-safe
src/balochi_nlp.egg-info/requires.txt
src/balochi_nlp.egg-info/top_level.txt
src/balochi_nlp/preprocessing/__init__.py
src/balochi_nlp/preprocessing/cleaner.py
src/balochi_nlp/preprocessing/normalizer.py
src/balochi_nlp/preprocessing/stopwords.py
src/balochi_nlp/resources/README.md
src/balochi_nlp/resources/stopwords/README.md
src/balochi_nlp/resources/stopwords/balochi.txt
src/balochi_nlp/tokenizers/__init__.py
src/balochi_nlp/tokenizers/sentence_tokenizer.py
src/balochi_nlp/tokenizers/word_tokenizer.py
src/balochi_nlp/utils/__init__.py
src/balochi_nlp/utils/file_utils.py
tests/__init__.py
tests/conftest.py
tests/test_cleaner.py
tests/test_stopwords.py
tests/test_tokenizer.py