Metadata-Version: 2.4
Name: balochi-nlp
Version: 1.0.1
Summary: A comprehensive Natural Language Processing toolkit for the Balochi language
Home-page: https://github.com/hafeezBaluch/balochi-nlp
Author: Hafeez Baloch
Author-email: Hafeez Baloch <hafeezullahhassan2019@gmail.com>
License: MIT License
Requires-Python: >=3.8
License-File: LICENSE
Requires-Dist: numpy>=1.21.0
Requires-Dist: pandas>=1.3.0
Requires-Dist: nltk>=3.6.0
Requires-Dist: scikit-learn>=0.24.0
Requires-Dist: regex>=2023.0.0
Requires-Dist: tqdm>=4.65.0
Provides-Extra: dev
Requires-Dist: pytest>=7.0; extra == "dev"
Requires-Dist: pytest-cov>=4.0; extra == "dev"
Requires-Dist: black>=22.0; extra == "dev"
Requires-Dist: isort>=5.0; extra == "dev"
Requires-Dist: flake8>=4.0; extra == "dev"
Requires-Dist: mypy>=0.9; extra == "dev"
Requires-Dist: tox>=3.24; extra == "dev"
Requires-Dist: sphinx>=4.5.0; extra == "dev"
Requires-Dist: sphinx-rtd-theme>=1.0.0; extra == "dev"
Dynamic: author
Dynamic: home-page
Dynamic: license-file
Dynamic: requires-python
